LICENSE
README.md
setup.py
pesqc2/__init__.py
pesqc2/_pesq.py
pesqc2/cypesq.pyx
pesqc2/dsp.c
pesqc2/dsp.h
pesqc2/pesq.h
pesqc2/pesqdsp.c
pesqc2/pesqio.h
pesqc2/pesqmain.h
pesqc2/pesqmod.c
pesqc2/pesqpar.h
pesqc2.egg-info/PKG-INFO
pesqc2.egg-info/SOURCES.txt
pesqc2.egg-info/dependency_links.txt
pesqc2.egg-info/requires.txt
pesqc2.egg-info/top_level.txt
tests/test_pesq.py