Metadata-Version: 2.4
Name: pesqc2
Version: 0.0.4
Summary: Python Wrapper for PESQ Score (narrow band and wide band) - including Corrigendum 2
Home-page: https://github.com/audiolabs/PESQ
Author: mtorcoli, ModarHalimeh, ludlows
Classifier: Programming Language :: Python
Classifier: License :: OSI Approved :: MIT License
Classifier: Operating System :: OS Independent
License-File: LICENSE
Requires-Dist: numpy<2.0
Dynamic: author
Dynamic: classifier
Dynamic: description
Dynamic: description-content-type
Dynamic: home-page
Dynamic: license-file
Dynamic: requires-dist
Dynamic: summary
